main.py
covid19_dashboard/__init__.py
covid19_dashboard/config.py
covid19_dashboard/covid_data_handler.py
covid19_dashboard/covid_news_handler.py
covid19_dashboard/data_handler.py
covid19_dashboard/static/favicon.ico
covid19_dashboard/static/images
covid19_dashboard/static/reshot-icon-covid-19-PCU94GRABZ.ico:Zone.Identifier
covid19_dashboard/static/reshot-icon-covid-19-PCU94GRABZ.svg:Zone.Identifier
covid19_dashboard/templates/index.html
dashboard/__init__.py
dashboard/config.py
dashboard/covid_data_handler.py
dashboard/covid_news_handler.py
dashboard/data_handler.py
rillian_grant_university_project_covid19_dashboard-1.0.2.dist-info/LICENSE
rillian_grant_university_project_covid19_dashboard-1.0.2.dist-info/METADATA
rillian_grant_university_project_covid19_dashboard-1.0.2.dist-info/WHEEL
rillian_grant_university_project_covid19_dashboard-1.0.2.dist-info/entry_points.txt
rillian_grant_university_project_covid19_dashboard-1.0.2.dist-info/top_level.txt
rillian_grant_university_project_covid19_dashboard-1.0.2.dist-info/RECORD
